zeusai_py/__init__.py
zeusai_py/exceptions.py
zeusai_py/io/__init__.py
zeusai_py/io/__main__.py
zeusai_py/io/_socket_io.py
zeusai_py/io/client.py
zeusai_py/io/exceptions.py
zeusai_py/plugin/__init__.py
zeusai_py/plugin/plugin.py
zeusai_py-0.0.1.1.dist-info/WHEEL
zeusai_py-0.0.1.1.dist-info/METADATA
zeusai_py-0.0.1.1.dist-info/RECORD
