Metadata-Version: 2.1
Name: zeusai-py
Version: 0.0.1.1
Summary: 
Home-page: https://github.com/joshinshaker-tech/zeusai_py
Author: JMT
Author-email: contact@joshinshaker.com
Requires-Python: >=3.7,<4.0
Classifier: Programming Language :: Python :: 3
Classifier: Programming Language :: Python :: 3.7
Classifier: Programming Language :: Python :: 3.8
Classifier: Programming Language :: Python :: 3.9
Project-URL: Repository, https://github.com/joshinshaker-tech/zeusai_py
